sapsec/__init__.py
sapsec/__main__.py
sapsec/rules_config.yaml
sapsec/sapanalysis.py
sapsec/settings.py
sapsec/checks/__init__.py
sapsec/checks/composite_check.py
sapsec/checks/elementary_check.py
sapsec/checks/manager.py
sapsec/checks/profile_param.py
sapsec/checks/security_check.py
sapsec/checks/software_comparation.py
sapsec/checks/table_check.py
sapsec/checks/table_entries.py
sapsec/checks/users_by_privileges.py
sapsec/excelreport/__init__.py
sapsec/excelreport/report.py
sapsec/excelreport/software_version.py
sapsec/excelreport/xlsxreport.py
sapsec/sapgui/__init__.py
sapsec/sapgui/reports.py
sapsec/sapgui/rpsfpar.py
sapsec/sapgui/rsusr002.py
sapsec/sapgui/rsusr070.py
sapsec/sapgui/saplogon.py
sapsec/sapgui/savetofile.py
sapsec/sapgui/se16.py
sapsec/sapgui/transactions.py
sapsec-1.0.2.dist-info/LICENSE
sapsec-1.0.2.dist-info/METADATA
sapsec-1.0.2.dist-info/WHEEL
sapsec-1.0.2.dist-info/entry_points.txt
sapsec-1.0.2.dist-info/top_level.txt
sapsec-1.0.2.dist-info/RECORD
