Metadata-Version: 2.1
Name: sapsec
Version: 1.0.2
Summary: SAP security analysis tool using SAP GUI scripting
Home-page: https://github.com/gutskodv/sap-security
Author: Dmitry Gutsko
Author-email: gutskodv@gmail.com
License: GPL v2
Platform: UNKNOWN
Requires-Dist: pywin32 (>=227)
Requires-Dist: XlsxWriter (>=1.2.8)
Requires-Dist: PyYAML (>=5.3.1)
Requires-Dist: PySapGUI (>=1.0.5)
